[
    {
        "key": "dbln",
        "value": "%7B%22100095281356298%22%3A%22Djr8t2qh%22%2C%22100095041339108%22%3A%22zwNthsj9%22%2C%2261565531410030%22%3A%22qrtwepGS%22%7D",
        "domain": "facebook.com",
        "path": "/login/device-based/",
        "hostOnly": false,
        "creation": "2024-10-07T03:45:26.673Z",
        "lastAccessed": "2024-10-07T03:45:26.681Z"
    },
    {
        "key": "datr",
        "value": "Q4T2ZlWRleYNMmLNY33KuFTg",
        "domain": "facebook.com",
        "path": "/",
        "hostOnly": false,
        "creation": "2024-10-07T03:45:26.681Z",
        "lastAccessed": "2024-10-07T03:45:26.681Z"
    },
    {
        "key": "sb",
        "value": "Q4T2ZrTR6kB-mqNHqhPXwi0r",
        "domain": "facebook.com",
        "path": "/",
        "hostOnly": false,
        "creation": "2024-10-07T03:45:26.681Z",
        "lastAccessed": "2024-10-07T03:45:26.681Z"
    },
    {
        "key": "ps_l",
        "value": "1",
        "domain": "facebook.com",
        "path": "/",
        "hostOnly": false,
        "creation": "2024-10-07T03:45:26.681Z",
        "lastAccessed": "2024-10-07T03:45:26.681Z"
    },
    {
        "key": "ps_n",
        "value": "1",
        "domain": "facebook.com",
        "path": "/",
        "hostOnly": false,
        "creation": "2024-10-07T03:45:26.681Z",
        "lastAccessed": "2024-10-07T03:45:26.681Z"
    },
    {
        "key": "dpr",
        "value": "1.9790045022964478",
        "domain": "facebook.com",
        "path": "/",
        "hostOnly": false,
        "creation": "2024-10-07T03:45:26.681Z",
        "lastAccessed": "2024-10-07T03:45:26.681Z"
    },
    {
        "key": "vpd",
        "value": "v1%3B878x463x1.556249976158142",
        "domain": "facebook.com",
        "path": "/",
        "hostOnly": false,
        "creation": "2024-10-07T03:45:26.681Z",
        "lastAccessed": "2024-10-07T03:45:26.681Z"
    },
    {
        "key": "wl_cbv",
        "value": "v2%3Bclient_version%3A2635%3Btimestamp%3A1728186456",
        "domain": "facebook.com",
        "path": "/",
        "hostOnly": false,
        "creation": "2024-10-07T03:45:26.681Z",
        "lastAccessed": "2024-10-07T03:45:26.681Z"
    },
    {
        "key": "c_user",
        "value": "61565531410030",
        "domain": "facebook.com",
        "path": "/",
        "hostOnly": false,
        "creation": "2024-10-07T03:45:26.681Z",
        "lastAccessed": "2024-10-07T03:45:26.681Z"
    },
    {
        "key": "fr",
        "value": "1zDm1fXu79SnoPCtr.AWVmoPhskVTExUHtw27b6daBwoE.BnABXR..AAA.0.0.BnAt7g.AWWaEIv1QPw",
        "domain": "facebook.com",
        "path": "/",
        "hostOnly": false,
        "creation": "2024-10-07T03:45:26.681Z",
        "lastAccessed": "2024-10-07T03:45:26.681Z"
    },
    {
        "key": "xs",
        "value": "50%3Aq__VaPbcvsKUqg%3A2%3A1728241377%3A-1%3A10524",
        "domain": "facebook.com",
        "path": "/",
        "hostOnly": false,
        "creation": "2024-10-07T03:45:26.681Z",
        "lastAccessed": "2024-10-07T03:45:26.681Z"
    },
    {
        "key": "locale",
        "value": "en_US",
        "domain": "facebook.com",
        "path": "/",
        "hostOnly": false,
        "creation": "2024-10-07T03:45:26.681Z",
        "lastAccessed": "2024-10-07T03:45:26.681Z"
    },
    {
        "key": "m_page_voice",
        "value": "61565531410030",
        "domain": "facebook.com",
        "path": "/",
        "hostOnly": false,
        "creation": "2024-10-07T03:45:26.681Z",
        "lastAccessed": "2024-10-07T03:45:26.681Z"
    },
    {
        "key": "m_pixel_ratio",
        "value": "1.556249976158142",
        "domain": "facebook.com",
        "path": "/",
        "hostOnly": false,
        "creation": "2024-10-07T03:45:26.681Z",
        "lastAccessed": "2024-10-07T03:45:26.681Z"
    },
    {
        "key": "wd",
        "value": "463x878",
        "domain": "facebook.com",
        "path": "/",
        "hostOnly": false,
        "creation": "2024-10-07T03:45:26.681Z",
        "lastAccessed": "2024-10-07T03:45:26.681Z"
    },
    {
        "key": "fbl_st",
        "value": "100432047%3BT%3A28804542",
        "domain": "facebook.com",
        "path": "/",
        "hostOnly": false,
        "creation": "2024-10-07T03:45:26.681Z",
        "lastAccessed": "2024-10-07T03:45:26.682Z"
    }
]
